{
  "version": 1,
  "type": "paper",
  "id": "2026-06-07-arabica-rootstock-robusta-drought",
  "date": "2026-06-07",
  "slug": "arabica-rootstock-robusta-drought",
  "title_ko": "뿌리를 바꿔 가뭄을 버틴다 — 아라비카 대목에 접붙인 로부스타의 물 부족 생리 성능",
  "title_original": "Adopting coffee to climate change: arabica rootstocks enhance physiological performance of robusta under water deficit",
  "one_liner": "로부스타를 아라비카 뿌리(대목)에 접붙이니 가뭄 스트레스에서 광합성 감소 −7.7%에 그쳐 — 3년 묘목 시험으로 본 기후 적응 전략",
  "authors": "Patil et al.",
  "journal": "Frontiers in Climate",
  "pub_date": "2026-01-23",
  "doi": "10.3389/fclim.2025.1748714",
  "categories_primary": [
    "지속가능성/경제"
  ],
  "categories_secondary": [
    "생두",
    "공학"
  ],
  "summary": "기후변화로 가뭄이 잦아지는 가운데, 로부스타 커피 가지(접수)를 아라비카 뿌리(대목)에 접붙이는 '접목'으로 가뭄 내성을 높일 수 있는지 3년에 걸쳐 묘목에서 검증한 연구. 최우수 조합인 S.4595/C×R는 가뭄 스트레스에서도 순광합성 감소가 −7.7%로 가장 작았고, 스트레스 후 회복력도 가장 높았다. 또 높은 상대수분함량(79.63%)과 두꺼운 표피 왁스층(29.90 µg/cm²)을 유지했고 엽록소 a·b도 더 잘 보존했다. 뿌리(대목)를 바꾸는 것만으로 같은 품종이 물 부족을 더 잘 견딜 수 있음을 보여, 기후 탄력적 커피 재배의 실마리를 제시한다.",
  "key_findings": [
    "아라비카 대목에 접붙인 로부스타 — 가뭄 스트레스에서 순광합성 감소가 −7.7%로 최소(우수 조합 S.4595/C×R)",
    "스트레스 종료 후 회복력(post-stress recovery)도 우수 조합에서 가장 높음",
    "높은 상대수분함량(RWC) 79.63% 유지 — 잎이 물을 더 잘 붙잡음",
    "표피 왁스(epicuticular wax) 29.90 µg/cm²로 두꺼워 수분 증발 방어",
    "엽록소 a·b를 더 잘 보존 + 내재적 물 이용 효율(WUE) 향상"
  ],
  "methodology": "3년간 묘포(nursery) 시험. 로부스타 접수를 여러 아라비카 대목에 접목한 조합들을 가뭄(수분 결핍) 처리 → 순광합성, 상대수분함량(RWC), 표피 왁스량, 엽록소 a·b, 물 이용 효율(WUE), 스트레스 후 회복을 측정·비교.",
  "implications": {
    "농가/가공장": "품종을 바꾸지 않고 '뿌리(대목)'만 골라 접붙여도 가뭄을 더 잘 견디게 만들 수 있는 실용 전략. 물이 부족한 산지의 적응 옵션.",
    "로스터/큐그레이더": "기후 스트레스에 강한 재배 방식이 공급 안정성과 직결 — 가뭄 해에도 품질·수율 변동을 줄일 가능성. 산지 다변화·리스크 관리 관점에서 주목.",
    "R&D": "묘목 단계 결과라 성목·실제 포장(圃場) 수율·컵 품질로의 연결 검증 필요. 대목-접수 궁합의 생리 기전, 다지역 재현이 후속 과제."
  },
  "limitations": "묘목(nursery) 단계 3년 시험 — 성목의 장기 수율·컵 품질로 직접 이어진다는 보장은 아직 없음; 특정 대목-접수 조합·시험지 환경 중심; 실제 농가 포장 조건·병해충 상호작용은 추가 검증 필요.",
  "glossary": [
    {
      "term": "접목 (Grafting)",
      "ko": "한 식물의 뿌리(대목)에 다른 식물의 가지(접수)를 이어 붙여 한 그루로 키우는 기술. 과수에서 흔히 쓴다"
    },
    {
      "term": "대목 (Rootstock)",
      "ko": "접목에서 '뿌리' 역할을 맡는 아래쪽 식물. 여기서는 가뭄에 강한 아라비카 계통이 대목"
    },
    {
      "term": "접수 (Scion)",
      "ko": "접목에서 '가지·열매' 역할을 맡는 위쪽 식물. 여기서는 우리가 수확하려는 로부스타"
    },
    {
      "term": "순광합성",
      "ko": "식물이 빛으로 만든 양분에서 호흡으로 쓴 양을 뺀 '실질 생산량'. 가뭄에 줄어든다"
    },
    {
      "term": "상대수분함량 (RWC)",
      "ko": "잎이 가득 머금을 수 있는 물 대비 현재 머금은 물의 비율. 높을수록 가뭄을 잘 버틴다"
    },
    {
      "term": "표피 왁스 (Epicuticular wax)",
      "ko": "잎 표면을 덮는 왁스층. 두꺼울수록 수분 증발과 햇빛 손상을 막는 방패가 된다"
    },
    {
      "term": "물 이용 효율 (WUE)",
      "ko": "물 한 방울로 얼마나 많은 광합성을 하는지의 효율. 높을수록 물을 알뜰하게 쓴다"
    }
  ],
  "easy_hero_emoji": "🌵",
  "easy_hero_title": "뿌리를 바꾸면 커피나무가 가뭄을 더 잘 견딘다고?",
  "easy_intro_paragraphs": [
    "기후변화로 커피 재배지에 가뭄이 점점 잦아지고 있어. 커피나무는 물이 부족하면 광합성을 잘 못 하고, 그러면 열매도 적게 맺고 맛도 떨어져. 농가 입장에선 진짜 큰 문제야.",
    "그래서 연구진은 재미있는 방법을 시도했어. 나무 전체를 바꾸는 게 아니라, '뿌리'만 가뭄에 강한 종류로 바꿔서 그 위에 우리가 원하는 가지를 접붙인 거야. 이걸 '접목'이라고 해.",
    "구체적으로는 가뭄에 비교적 강한 아라비카를 '뿌리(대목)'로 쓰고, 그 위에 로부스타 가지를 올렸어. 그리고 3년 동안 일부러 물을 적게 주면서 어떤 조합이 잘 버티는지 관찰했지."
  ],
  "easy_concepts": [
    {
      "title": "1️⃣ 접목이 뭐야?",
      "body": "접목은 한 나무의 뿌리에 다른 나무의 가지를 이어 붙여서 한 그루로 키우는 기술이야. 아래(뿌리)는 튼튼한 걸 쓰고, 위(가지·열매)는 맛있는 걸 쓰는 식이지. 사과·포도 농사에선 아주 흔해.",
      "analogy": "비유: 튼튼한 운동화 밑창(뿌리)에 예쁜 윗부분(가지)을 붙여 신는 거랑 비슷해. 밑창이 좋으면 오래 잘 걷지."
    },
    {
      "title": "2️⃣ 잎이 물을 붙잡는 힘 (RWC)",
      "body": "상대수분함량(RWC)은 잎이 물을 얼마나 머금고 있는지를 보여주는 숫자야. 가뭄이 와도 이 값이 높게 유지되면, 그 나무는 물을 잘 붙잡고 버티는 거지.",
      "analogy": "비유: 같은 사막에서도 물통을 꽉 쥐고 있는 사람이 더 오래 버티는 거랑 같아."
    },
    {
      "title": "3️⃣ 잎의 왁스 방패",
      "body": "잎 표면엔 얇은 왁스층이 있어. 이게 두꺼우면 물이 증발해 날아가는 걸 막아주는 방패가 돼. 우수 조합은 이 왁스층이 더 두꺼웠어(29.90 µg/cm²).",
      "analogy": "비유: 입술이 트지 말라고 립밤을 바르는 거랑 똑같아. 왁스가 수분을 가둬주는 거지."
    }
  ],
  "easy_findings": [
    {
      "medal": "gold",
      "title": "🥇 가뭄에도 광합성 거의 안 줄었다",
      "body": "최고 조합(S.4595/C×R)은 가뭄 스트레스에서 순광합성 감소가 −7.7%밖에 안 됐어. 다른 조합보다 훨씬 잘 버틴 거야."
    },
    {
      "medal": "silver",
      "title": "🥈 물을 꽉 붙잡았다 (RWC 79.63%)",
      "body": "잎의 상대수분함량을 79.63%로 높게 유지했어. 가뭄에도 잎이 물을 잘 안 놓쳤다는 뜻이야."
    },
    {
      "medal": "bronze",
      "title": "🥉 왁스 방패가 두꺼웠다 (29.90 µg/cm²)",
      "body": "잎 표면 왁스가 두꺼워서 수분 증발을 잘 막았고, 엽록소 a·b도 더 잘 지켜냈어."
    },
    {
      "medal": "medal",
      "title": "🏅 스트레스 끝난 뒤 회복도 빨랐다",
      "body": "가뭄이 끝난 뒤 다시 기운을 차리는 회복력도 우수 조합이 제일 좋았어. 잠깐 힘들어도 금방 돌아온 거지."
    }
  ],
  "easy_tables": [
    {
      "title": "🆚 보통 묘목 vs 아라비카 대목 접목 (가뭄 시)",
      "headers": [
        "항목",
        "취약 조합",
        "우수 조합(S.4595/C×R)"
      ],
      "rows": [
        [
          "광합성 감소",
          "더 크게 줄어듦",
          "−7.7% (최소)"
        ],
        [
          "잎 수분(RWC)",
          "잘 못 붙잡음",
          "79.63% 유지"
        ],
        [
          "왁스 방패",
          "얇음",
          "29.90 µg/cm² (두꺼움)"
        ],
        [
          "회복력",
          "느림",
          "가장 빠름"
        ]
      ]
    }
  ],
  "easy_summary": "나무 전체가 아니라 '뿌리(대목)'만 가뭄에 강한 아라비카로 바꿔 로부스타를 접붙였더니, 가뭄에서도 광합성 감소가 −7.7%에 그치고 물도 잘 붙잡고(RWC 79.63%) 회복도 빨랐어. 뿌리를 잘 고르는 것만으로 기후변화에 강한 커피를 만들 수 있다는 실마리야. (단, 묘목 단계 결과라 성목 검증은 아직 남았어!)",
  "citation_apa": "Patil [et al.] (2026). Adopting coffee to climate change: arabica rootstocks enhance physiological performance of robusta under water deficit. Frontiers in Climate, 7, 1748714. https://doi.org/10.3389/fclim.2025.1748714",
  "links": {
    "doi": "https://doi.org/10.3389/fclim.2025.1748714",
    "oa_pdf": "https://www.frontiersin.org/journals/climate/articles/10.3389/fclim.2025.1748714/full",
    "journal_homepage": "https://www.frontiersin.org/journals/climate"
  },
  "source_basis": "abstract_only",
  "data_charts": [
    {
      "title": "우수 조합 S.4595/C×R 가뭄 스트레스 지표",
      "unit": "",
      "x_labels": [
        "잎 수분 RWC(%)",
        "표피 왁스(µg/cm²)"
      ],
      "values": [
        79.63,
        29.9
      ]
    }
  ],
  "hero_image": "/static/img/insights/hero/sustainability.svg"
}